covid_cloud/__init__.py
covid_cloud/constants.py
covid_cloud/cli/auth/__init__.py
covid_cloud/cli/auth/commands.py
covid_cloud/cli/auth/utils.py
covid_cloud/cli/cli_config/__init__.py
covid_cloud/cli/cli_config/commands.py
covid_cloud/cli/files/__init__.py
covid_cloud/cli/files/commands.py
covid_cloud/cli/search/__init__.py
covid_cloud/cli/search/commands.py
covid_cloud/cli/search/tables/__init__.py
covid_cloud/cli/search/tables/commands.py
covid_cloud/client/__init__.py
covid_cloud/client/auth.py
covid_cloud/client/covid_cloud_client.py
covid_cloud/client/files_client.py
covid_cloud/client/search_client.py
covid_cloud/client/utils.py
covid_cloud_cli-0.0.17.dist-info/LICENSE
covid_cloud_cli-0.0.17.dist-info/METADATA
covid_cloud_cli-0.0.17.dist-info/WHEEL
covid_cloud_cli-0.0.17.dist-info/top_level.txt
covid_cloud_cli-0.0.17.dist-info/RECORD
